{"bpic15": {"key_pair": {}, "categorical_attrs": ["activity", "resource"], "maximum_prefix":45}, "bpic17": {"key_pair": {"Case ID": "caseid", "Activity": "activity", "Resource": "resource", "Start Timestamp": "ts"}, "categorical_attrs": ["activity", "resource"],"maximum_prefix":15}, "iro5k": {"key_pair": {"Case ID": "caseid", "Activity": "activity", "Complete Timestamp": "ts"}, "categorical_attrs": ["activity"],"maximum_prefix":12}, "road_traffic_fine_process": {"key_pair": {"Case ID": "caseid", "Activity": "activity", "Resource": "resource", "Complete Timestamp": "ts"}, "categorical_attrs": ["activity", "resource"],"maximum_prefix":6}}